pyul/__init__.py
pyul/archive.py
pyul/decoratorUtils.py
pyul/dll.py
pyul/ecs.py
pyul/envUtils.py
pyul/events.py
pyul/importUtils.py
pyul/loggingUtils.py
pyul/mathUtils.py
pyul/netUtils.py
pyul/platform.py
pyul/resources.py
pyul/threadUtils.py
pyul/xmlUtils.py
pyul/coreUtils/__init__.py
pyul/coreUtils/boolaction.py
pyul/coreUtils/classcontextmanager.py
pyul/coreUtils/common.py
pyul/coreUtils/compare.py
pyul/coreUtils/configs.py
pyul/coreUtils/dotifydict.py
pyul/coreUtils/event.py
pyul/coreUtils/filefinder.py
pyul/coreUtils/jitproxy.py
pyul/coreUtils/meta.py
pyul/coreUtils/singleton.py
pyul/guiUtils/__init__.py
pyul/guiUtils/qt/__init__.py
pyul/guiUtils/qt/binding_helper.py
pyul/support/__init__.py
pyul/support/path.py
pyul-0.4.5.dist-info/DESCRIPTION.rst
pyul-0.4.5.dist-info/LICENSE.txt
pyul-0.4.5.dist-info/METADATA
pyul-0.4.5.dist-info/metadata.json
pyul-0.4.5.dist-info/pbr.json
pyul-0.4.5.dist-info/RECORD
pyul-0.4.5.dist-info/top_level.txt
pyul-0.4.5.dist-info/WHEEL
