Metadata-Version: 2.0
Name: pyul
Version: 0.4.5
Summary: Python Utility Library - A library of utilities for python development
Home-page: https://github.com/rocktavious/pyul
Author: Kyle Rockman
Author-email: ['kyle.rockman@mac.com']
License: UNKNOWN
Platform: UNKNOWN
Requires-Dist: six
Requires-Dist: decorator
Requires-Dist: pathlib
Requires-Dist: unittest2
Requires-Dist: pyyaml
Requires-Dist: enum34
